{
    "0": "",
    "2": " this evening about",
    "3": "",
    "4": "",
    "5": "",
    "6": "",
    "7": "",
    "8": "",
    "9": " june 17 parliamentary elections",
    "10": "",
    "11": "",
    "12": "",
    "13": "",
    "14": "",
    "16": " un",
    "17": "",
    "18": "",
    "19": "",
    "20": " not far from iraq",
    "21": "",
    "22": "",
    "23": "",
    "25": " un",
    "26": " cafe at one of the",
    "27": "",
    "28": " crocodile cafe in the commercial district",
    "30": " morning rush hour",
    "31": "",
    "32": "",
    "39": " mcdonalds restaurant in istanbul",
    "43": "",
    "45": "",
    "46": "",
    "47": " tomorrow at noon eastern",
    "48": " today",
    "49": " new york",
    "50": " 1000 a",
    "53": "",
    "54": "",
    "55": " un",
    "56": "",
    "57": "",
    "58": " un",
    "60": "",
    "61": " today if they dont rat",
    "63": " second half of",
    "64": " last year",
    "67": " un",
    "68": " three days",
    "69": " a bomber blew herself up outside a",
    "76": "",
    "77": " twoday trip",
    "80": " today",
    "81": "",
    "84": "",
    "85": "",
    "86": "",
    "87": " 1992",
    "90": " pearl was murdered by terrorists in pakistan",
    "91": " northern ireland in belfast",
    "95": "",
    "101": "",
    "102": "",
    "103": "",
    "104": "",
    "105": "",
    "106": " un",
    "110": "",
    "112": " un",
    "115": "",
    "116": "",
    "117": "",
    "119": " capital",
    "121": "",
    "123": "",
    "124": "",
    "125": "",
    "131": "",
    "132": " on saturday",
    "133": "",
    "137": "",
    "138": "",
    "140": "",
    "144": "",
    "145": "",
    "146": "",
    "147": " gaza",
    "149": "",
    "150": " monday",
    "152": "",
    "153": "",
    "158": " baghdad",
    "159": "",
    "160": "",
    "161": "",
    "163": "",
    "164": " un",
    "165": "",
    "167": "",
    "170": " tom ridge just re resigned",
    "171": "",
    "172": "",
    "173": "",
    "178": "",
    "179": " un",
    "183": "",
    "185": "",
    "188": " los angelesarea hospital",
    "189": " un",
    "191": "",
    "192": " un",
    "195": "",
    "199": "",
    "203": "",
    "207": "",
    "209": " baghdad",
    "211": "",
    "212": "",
    "217": "",
    "218": " un",
    "219": " the white house",
    "221": "",
    "224": " tultuli 60",
    "225": " wednesday",
    "226": " agartala",
    "229": " june 8",
    "233": "",
    "234": " saturday",
    "235": "",
    "238": " last week",
    "241": "",
    "243": "",
    "246": "",
    "247": "",
    "249": " un",
    "251": " un",
    "254": " tuesday",
    "255": " sevenmonth",
    "256": " 158 p",
    "258": " january",
    "259": "",
    "260": "",
    "261": "",
    "263": "",
    "264": " un",
    "265": "",
    "266": " malaysian politics",
    "270": "",
    "271": "",
    "275": "",
    "277": "",
    "279": "",
    "280": " un",
    "281": "",
    "283": " april 21",
    "286": "",
    "287": " un",
    "290": "",
    "291": "",
    "296": "",
    "298": "",
    "301": "",
    "303": "",
    "306": "",
    "310": " parking lot",
    "316": "",
    "320": "",
    "322": "",
    "323": " los angeles superior court",
    "324": "",
    "326": "",
    "330": " pakistan",
    "331": "",
    "332": "",
    "334": "",
    "337": "",
    "340": " un",
    "347": " baghdad",
    "349": "",
    "351": "",
    "352": " monday",
    "353": "",
    "355": " late may",
    "360": "",
    "366": "",
    "368": "",
    "375": "",
    "376": " un",
    "377": "",
    "378": " un",
    "379": "",
    "380": " un",
    "385": "",
    "387": "",
    "388": "",
    "389": " nearly two years ago",
    "391": "",
    "392": " strip",
    "394": "",
    "395": "",
    "396": "",
    "397": "",
    "398": " un",
    "403": "",
    "406": "",
    "407": "",
    "409": " 20hour",
    "410": "",
    "411": "",
    "413": "",
    "416": "",
    "418": "",
    "419": " un",
    "421": "",
    "422": "",
    "425": " iraq",
    "428": " un",
    "429": "",
    "430": "",
    "432": "",
    "438": "",
    "441": "",
    "442": "",
    "445": " hillsborough south of belfast",
    "446": "",
    "449": "",
    "451": "",
    "454": "",
    "455": "",
    "456": "",
    "457": "",
    "459": "",
    "460": "",
    "461": "",
    "464": "",
    "467": "",
    "468": "",
    "469": ""
}